ninjarmm_api/__init__.py
ninjarmm_api/auth.py
ninjarmm_api/client.py
py_ninjarmm_api_client-0.0.3.dist-info/LICENSE
py_ninjarmm_api_client-0.0.3.dist-info/METADATA
py_ninjarmm_api_client-0.0.3.dist-info/WHEEL
py_ninjarmm_api_client-0.0.3.dist-info/top_level.txt
py_ninjarmm_api_client-0.0.3.dist-info/RECORD
