Metadata-Version: 2.1
Name: py-ninjarmm-api-client
Version: 0.0.3
Summary: Unoffical NinjaRMM API client in Python 3
Home-page: https://bitbucket.org/raptus-it-services/py-ninjarmm-api-client
Author: Guy Zuercher
Author-email: geeosor@gmail.com
License: UNKNOWN
Platform: UNKNOWN
Classifier: Programming Language :: Python :: 3
Classifier: License :: OSI Approved :: MIT License
Classifier: Operating System :: OS Independent
Requires-Dist: requests
